llama_index/embeddings/autoembeddings/__init__.py
llama_index/embeddings/autoembeddings/base.py
llama_index_embeddings_autoembeddings-0.2.1.dist-info/METADATA
llama_index_embeddings_autoembeddings-0.2.1.dist-info/WHEEL
llama_index_embeddings_autoembeddings-0.2.1.dist-info/licenses/LICENSE
llama_index_embeddings_autoembeddings-0.2.1.dist-info/RECORD
