Metadata-Version: 2.4
Name: llama-index-embeddings-autoembeddings
Version: 0.2.1
Summary: llama-index embeddings AutoEmbeddings integration
Author-email: Clelia Astra Bertelli <astraberte9@gmail.com>
License-Expression: MIT
License-File: LICENSE
Requires-Python: <4.0,>=3.9
Requires-Dist: chonkie[all]
Requires-Dist: llama-index-core<0.15,>=0.13.0
